mult.v
// An fixed-latency multiplier that produces its output on the 3rd cycle.
// cycle 0: in0 = 5, in1 = 6
// cycle 1: nothing
// cycle 2: nothing
// cycle 3: 30
module imul(
    input logic clk,
    input logic reset,

    input logic [31:0] in0,
    input logic [31:0] in1,

    output logic [31:0] out
);

    logic [31:0] mult_s1;
    logic [31:0] mult_s2;
    logic [31:0] mult_s3;
    logic [31:0] mult_s4;

    always_ff @(posedge clk) begin
        if (reset) begin
            mult_s1 <= 32'd0;
            mult_s2 <= 32'd0;
            mult_s3 <= 32'd0;
            mult_s4 <= 32'd0;
        end else begin
            mult_s1 <= in0 * in1;
            mult_s2 <= mult_s1;
            mult_s3 <= mult_s2;
            mult_s4 <= mult_s3;

        end
    end

    assign out = mult_s4;

endmodule

alu.v
`include "mult.v"

// A simple ALU for addition and multiplication. opsel = 1 means add, opsel = 0 means mult.
module alu
(
    input logic         clk,
    input logic         reset,

    input  logic [31:0] in0,
    input  logic [31:0] in1,
    input  logic        opsel,
    output logic [31:0] out
);

    logic [31:0] add_s0;
    assign add_s0 = in0 + in1;

    logic [31:0] add_s1;
    logic [31:0] add_s2;
    logic [31:0] add_s3;
    logic [31:0] add_result;

    always_ff @(posedge clk) begin
        if (reset) begin
            add_s1 <= 0;
            add_s2 <= 0;
            add_s3 <= 0;
            add_result <= 0;
        end else begin
            add_s1 <= in0 + in1;
            add_s2 <= add_s1;
            add_s3 <= add_s2;
            add_result <= add_s3;
        end
    end


    logic [31:0] mult_result;
    
    imul multiplier
    (
        .clk   (clk),
        .reset (reset),
        .in0   (in0),
        .in1   (in1),
        .out   (mult_result)
    );

    assign out = opsel ? add_result : mult_result;

endmodule

alu_tb.v
`include "alu.v"

module tb;

    logic reset = 1;

    logic clk = 1;
    always #5 clk = ~clk;

    logic        opsel;
    logic [31:0] in0;
    logic [31:0] in1;

    logic [31:0] out;

    alu my_alu
    (
        .*
    );

    initial begin
        $dumpfile("alu_tb.vcd");
        $dumpvars;

        #11;
        reset = 0;
        in0 = 2;
        in1 = 4;
        opsel = 1;
        #10;
        $display("cycle 0: in0 = %x, in1 = %x, opsel = %x", in0, in1, opsel);
        $display("cycle 0: out = %x", out);

        #10;
        $display("cycle 1: in0 = %x, in1 = %x, opsel = %x", in0, in1, opsel);
        $display("cycle 1: out = %x", out);

        #10;
        $display("cycle 2: in0 = %x, in1 = %x, opsel = %x", in0, in1, opsel);
        $display("cycle 2: out = %x", out);

        #10;
        $display("cycle 3: in0 = %x, in1 = %x, opsel = %x", in0, in1, opsel);
        $display("cycle 3: out = %x", out);

        reset = 1;
        #10;

        $display("cycle 4: reset = %x", reset);

        reset = 0;
        in0 = 2;
        in1 = 4;
        opsel = 0;
        #10;
        $display("cycle 5: in0 = %x, in1 = %x, opsel = %x", in0, in1, opsel);
        $display("cycle 5: out = %x", out);

        in0 = 'x;
        in1 = 'x;
        opsel = 0;
        #10;
        $display("cycle 6: in0 = %x, in1 = %x, opsel = %x", in0, in1, opsel);
        $display("cycle 6: out = %x", out);
        #10;
        $display("cycle 7: in0 = %x, in1 = %x, opsel = %x", in0, in1, opsel);
        $display("cycle 7: out = %x", out);
        #10;
        $display("cycle 8: in0 = %x, in1 = %x, opsel = %x", in0, in1, opsel);
        $display("cycle 8: out = %x", out);

        $finish;
    end



endmodule

alu_tb.vcd
$date
	Fri Sep 27 13:21:42 2024
$end
$version
	Icarus Verilog
$end
$timescale
	1s
$end
$scope module tb $end
$var wire 32 ! out [31:0] $end
$var reg 1 " clk $end
$var reg 32 # in0 [31:0] $end
$var reg 32 $ in1 [31:0] $end
$var reg 1 % opsel $end
$var reg 1 & reset $end
$scope module my_alu $end
$var wire 1 " clk $end
$var wire 32 ' in0 [31:0] $end
$var wire 32 ( in1 [31:0] $end
$var wire 1 % opsel $end
$var wire 1 & reset $end
$var wire 32 ) out [31:0] $end
$var wire 32 * mult_result [31:0] $end
$var wire 32 + add_s0 [31:0] $end
$var reg 32 , add_result [31:0] $end
$var reg 32 - add_s1 [31:0] $end
$var reg 32 . add_s2 [31:0] $end
$var reg 32 / add_s3 [31:0] $end
$scope module multiplier $end
$var wire 1 " clk $end
$var wire 32 0 in0 [31:0] $end
$var wire 32 1 in1 [31:0] $end
$var wire 32 2 out [31:0] $end
$var wire 1 & reset $end
$var reg 32 3 mult_s1 [31:0] $end
$var reg 32 4 mult_s2 [31:0] $end
$var reg 32 5 mult_s3 [31:0] $end
$var reg 32 6 mult_s4 [31:0] $end
$upscope $end
$upscope $end
$upscope $end
$enddefinitions $end
$comment Show the parameter values. $end
$dumpall
$end
#0
$dumpvars
bx 6
bx 5
bx 4
bx 3
bx 2
bx 1
bx 0
bx /
bx .
bx -
bx ,
bx +
bx *
bx )
bx (
bx '
1&
x%
bx $
bx #
1"
bx !
$end
#5
0"
#10
b0 *
b0 2
b0 6
b0 5
b0 4
b0 3
bx ,
bx /
bx .
bx -
1"
#11
1%
b110 +
b100 $
b100 (
b100 1
b10 #
b10 '
b10 0
0&
#15
0"
#20
b110 -
b1000 3
1"
#25
0"
#30
b1000 4
b110 .
1"
#35
0"
#40
b110 /
b1000 5
1"
#45
0"
#50
b110 !
b110 )
b1000 *
b1000 2
b1000 6
b110 ,
1"
#51
1&
#55
0"
#60
b110 ,
b110 /
b110 .
b110 -
b0 *
b0 2
b0 6
b0 5
b0 4
b0 3
1"
#61
b0 !
b0 )
0%
0&
#65
0"
#70
b1000 3
1"
#71
bx $
bx (
bx 1
bx +
bx #
bx '
bx 0
#75
0"
#80
bx -
b1000 4
bx 3
1"
#85
0"
#90
b1000 5
bx 4
bx .
1"
#95
0"
#100
b1000 !
b1000 )
bx /
b1000 *
b1000 2
b1000 6
bx 5
1"
